cdk_cloudformation_snowflake_database_database/__init__.py
cdk_cloudformation_snowflake_database_database/py.typed
cdk_cloudformation_snowflake_database_database/_jsii/__init__.py
cdk_cloudformation_snowflake_database_database/_jsii/snowflake-database-database@1.4.0-alpha.7.jsii.tgz
cdk_cloudformation_snowflake_database_database-1.4.0a7.dist-info/LICENSE
cdk_cloudformation_snowflake_database_database-1.4.0a7.dist-info/METADATA
cdk_cloudformation_snowflake_database_database-1.4.0a7.dist-info/WHEEL
cdk_cloudformation_snowflake_database_database-1.4.0a7.dist-info/top_level.txt
cdk_cloudformation_snowflake_database_database-1.4.0a7.dist-info/RECORD
